up_ibacop/__init__.py
up_ibacop/ibacop.py
up_ibacop/model/RotationForest.model
up_ibacop/model/global_features_simply.arff
up_ibacop/utils/features/ff-learner/roller3.0
up_ibacop/utils/features/heuristics/training.sh
up_ibacop/utils/features/heuristics/preprocess/preprocess
up_ibacop/utils/features/heuristics/search/dispatch
up_ibacop/utils/features/heuristics/search/downward
up_ibacop/utils/features/heuristics/search/downward-1
up_ibacop/utils/features/heuristics/search/downward-2
up_ibacop/utils/features/heuristics/search/downward-4
up_ibacop/utils/features/heuristics/search/unitcost
up_ibacop/utils/features/heuristics/translate/additive-hmax.py
up_ibacop/utils/features/heuristics/translate/axiom_rules.py
up_ibacop/utils/features/heuristics/translate/axiom_rules.pyc
up_ibacop/utils/features/heuristics/translate/build_model.py
up_ibacop/utils/features/heuristics/translate/build_model.pyc
up_ibacop/utils/features/heuristics/translate/constraints.py
up_ibacop/utils/features/heuristics/translate/constraints.pyc
up_ibacop/utils/features/heuristics/translate/fact_groups.py
up_ibacop/utils/features/heuristics/translate/fact_groups.pyc
up_ibacop/utils/features/heuristics/translate/graph.py
up_ibacop/utils/features/heuristics/translate/graph.pyc
up_ibacop/utils/features/heuristics/translate/greedy_join.py
up_ibacop/utils/features/heuristics/translate/greedy_join.pyc
up_ibacop/utils/features/heuristics/translate/instantiate.py
up_ibacop/utils/features/heuristics/translate/instantiate.pyc
up_ibacop/utils/features/heuristics/translate/invariant_finder.py
up_ibacop/utils/features/heuristics/translate/invariant_finder.pyc
up_ibacop/utils/features/heuristics/translate/invariants.py
up_ibacop/utils/features/heuristics/translate/invariants.pyc
up_ibacop/utils/features/heuristics/translate/normalize.py
up_ibacop/utils/features/heuristics/translate/normalize.pyc
up_ibacop/utils/features/heuristics/translate/pddl_to_prolog.py
up_ibacop-0.0.5.dist-info/LICENSE
up_ibacop-0.0.5.dist-info/METADATA
up_ibacop-0.0.5.dist-info/WHEEL
up_ibacop-0.0.5.dist-info/top_level.txt
up_ibacop-0.0.5.dist-info/RECORD
