Metadata-Version: 2.1
Name: up-ibacop
Version: 0.0.5
Summary: up_ibacop
Author: Isabel Cenamor and Tomas de la Rosa and Fernando Fernandez
Author-email: icenamorg@gmail.com
License: APACHE
Classifier: Operating System :: POSIX :: Linux
Requires-Python: >=3.7
License-File: LICENSE
